plate_simulation/__init__.py
plate_simulation/driver.py
plate_simulation/logger.py
plate_simulation/mesh/__init__.py
plate_simulation/mesh/options.py
plate_simulation/models/__init__.py
plate_simulation/models/events.py
plate_simulation/models/options.py
plate_simulation/models/plates.py
plate_simulation/models/series.py
plate_simulation/options.py
plate_simulation/utils.py
plate_simulation-assets/__init__.py
plate_simulation-assets/demo.geoh5
plate_simulation-assets/uijson/plate_simulation.ui.json
plate_simulation-0.2.0.dist-info/LICENSE
plate_simulation-0.2.0.dist-info/METADATA
plate_simulation-0.2.0.dist-info/WHEEL
plate_simulation-0.2.0.dist-info/RECORD
