Metadata-Version: 2.3
Name: plate-simulation
Version: 0.2.0
Summary:     Specialized mesh, model, and simulation for a parameterization of the halfspace + overburden and plate geological setting
License: MIT
Keywords: geology,geophysics,modelling,simulation
Author: Mira Geoscience
Author-email: support@mirageoscience.com
Maintainer: Benjamin Kary
Maintainer-email: benjamink@mirageoscience.com
Requires-Python: >=3.10,<4.0
Classifier: Development Status :: 4 - Beta
Classifier: Intended Audience :: Science/Research
Classifier: License :: OSI Approved :: MIT License
Classifier: Natural Language :: English
Classifier: Operating System :: MacOS
Classifier: Operating System :: Microsoft :: Windows
Classifier: Operating System :: POSIX
Classifier: Operating System :: Unix
Classifier: Programming Language :: Python
Classifier: Programming Language :: Python :: 3
Classifier: Programming Language :: Python :: 3.10
Classifier: Programming Language :: Python :: 3.11
Classifier: Programming Language :: Python :: 3.12
Classifier: Programming Language :: Python :: 3.13
Classifier: Topic :: Scientific/Engineering
Classifier: Topic :: Scientific/Engineering :: Mathematics
Classifier: Topic :: Scientific/Engineering :: Physics
Requires-Dist: Rtree (>=1.2.0,<1.3.0)
Requires-Dist: geoapps-utils (>=0.5.0,<0.6.dev)
Requires-Dist: geoh5py (>=0.11.0,<0.12.dev)
Requires-Dist: numpy (>=1.26.0,<1.27.0)
Requires-Dist: octree-creation-app (>=0.3.0,<0.4.dev)
Requires-Dist: param-sweeps (>=0.2.1,<0.3.dev)
Requires-Dist: pydantic (>=2.5.2,<3.0.0)
Requires-Dist: scipy (>=1.14.0,<1.15.0)
Requires-Dist: simpeg-drivers (>=0.3.0,<0.4.dev)
Requires-Dist: threadpoolctl (>=3.3.0,<3.4.0)
Requires-Dist: trimesh (>=4.1.3,<4.2.0)
Project-URL: Documentation, https://mirageoscience-plate-simulation.readthedocs-hosted.com/
Project-URL: Homepage, https://www.mirageoscience.com/mining-industry-software/python-integration/
Project-URL: Repository, https://github.com/MiraGeoscience/plate-simulation
